Metadata-Version: 2.4
Name: iflow-mcp_fs-mcp-py
Version: 0.1.1
Summary: Add your description here
Requires-Python: >=3.12
Requires-Dist: fastmcp>=2.11.2
Requires-Dist: pathspec>=0.12.1
